bindry/__init__.py
bindry/_version.py
bindry/config.py
bindry/context.py
bindry/decorators.py
bindry/exceptions.py
bindry/loader.py
bindry/scope.py
bindry/utils.py
bindry-0.1.4.dist-info/LICENSE
bindry-0.1.4.dist-info/METADATA
bindry-0.1.4.dist-info/WHEEL
bindry-0.1.4.dist-info/top_level.txt
bindry-0.1.4.dist-info/RECORD
